.flake8
.gitignore
.pre-commit-config.yaml
MANIFEST.in
README.md
pyproject.toml
setup.py
.github/workflows/build_and_test.yml
docs/.readthedocs.yml
docs/Makefile
docs/conf.py
docs/index.md
docs/make.bat
docs/_templates/autoapi/index.rst
examples/rzygi.py
examples/test.py
omnisolver/bruteforce/__init__.py
omnisolver/bruteforce/cpu/__init__.py
omnisolver/bruteforce/cpu/chunking.py
omnisolver/bruteforce/cpu/gray_code.py
omnisolver/bruteforce/gpu/__init__.py
omnisolver/bruteforce/gpu/gpu.yml
omnisolver/bruteforce/gpu/sampler.py
omnisolver/extensions/bruteforce_gpu.cu
omnisolver/extensions/bruteforce_gpu.h
omnisolver/extensions/bruteforce_wrapper_gpu.cpp
omnisolver/extensions/bruteforce_wrapper_gpu.pyx
omnisolver/extensions/vectors.h
omnisolver_bruteforce.egg-info/PKG-INFO
omnisolver_bruteforce.egg-info/SOURCES.txt
omnisolver_bruteforce.egg-info/dependency_links.txt
omnisolver_bruteforce.egg-info/entry_points.txt
omnisolver_bruteforce.egg-info/requires.txt
omnisolver_bruteforce.egg-info/top_level.txt
tests/cpu/__init__.py
tests/cpu/test_chunking.py
tests/cpu/test_gray_code.py
tests/gpu/__init__.py
tests/gpu/test_bruteforce_gpu_sampler.py