Metadata-Version: 2.1
Name: omnisolver-bruteforce
Version: 0.0.3
Summary: Bruteforce (a.k.a. exhaustive search) Plugin for Omnisolver
Project-URL: repository, https://github.com/euro-hpc-pl/omnisolver-bruteforce
Requires-Python: <3.10,>=3.7
Provides-Extra: docs
